sparkts/__init__.py
sparkts/_version.py
sparkts/datetimeindex.py
sparkts/timeseriesrdd.py
sparkts/utils.py
sparkts/models/ARGARCH.py
sparkts/models/ARIMA.py
sparkts/models/Autoregression.py
sparkts/models/AutoregressionX.py
sparkts/models/EWMA.py
sparkts/models/GARCH.py
sparkts/models/RegressionARIMA.py
sparkts/models/__init__.py
sparkts/models/_model.py
sparkts/models/test/__init__.py
sparkts/models/test/test_ARIMA.py
sparkts/models/test/test_Autoregression.py
sparkts/models/test/test_AutoregressionX.py
sparkts/models/test/test_EWMA.py
sparkts/models/test/test_GARCH.py
sparkts/models/test/test_RegressionARIMA.py
sparkts/test/__init__.py
sparkts/test/test_datetimeindex.py
sparkts/test/test_timeseriesrdd.py
sparkts/test/test_utils.py
sparktsX-0.3.0.dist-info/METADATA
sparktsX-0.3.0.dist-info/WHEEL
sparktsX-0.3.0.dist-info/top_level.txt
sparktsX-0.3.0.dist-info/RECORD
